apted/__init__.py
apted/__main__.py
apted/all_possible_mappings_ted.py
apted/apted.py
apted/config.py
apted/helpers.py
apted/node_indexer.py
apted/single_path_functions.py
apted/resources/correctness_test_cases.json
apted/resources/mini.json
apted/tests/__init__.py
apted/tests/test_chained.py
apted/tests/test_correctness.py
apted/tests/test_per_edit_operation_correctness.py
apted-1.0.3.dist-info/DESCRIPTION.rst
apted-1.0.3.dist-info/METADATA
apted-1.0.3.dist-info/RECORD
apted-1.0.3.dist-info/WHEEL
apted-1.0.3.dist-info/metadata.json
apted-1.0.3.dist-info/top_level.txt
