Metadata-Version: 1.1
Name: apted
Version: 1.0.3
Summary: APTED algorithm for the Tree Edit Distance
Home-page: https://github.com/JoaoFelipe/apted
Author: Joao Pimentel
Author-email: joaofelipenp@gmail.com
License: MIT
Keywords: APTED TED tree edit distance
Platform: UNKNOWN
Classifier: Development Status :: 5 - Production/Stable
Classifier: Intended Audience :: Science/Research
Classifier: Intended Audience :: Developers
Classifier: Topic :: Software Development :: Build Tools
Classifier: License :: OSI Approved :: MIT License
Classifier: Programming Language :: Python :: 2
Classifier: Programming Language :: Python :: 2.7
Classifier: Programming Language :: Python :: 3
Classifier: Programming Language :: Python :: 3.4
Classifier: Programming Language :: Python :: 3.5
Classifier: Programming Language :: Python :: 3.6
